{
  "type": "FeatureCollection",
  "features": [
    {
      "geometry": {
        "type": "Polygon",
        "coordinates": [
          [
            [
              -92.80410230000001,
              46.0852419
            ],
            [
              -92.8040923,
              46.0707518
            ],
            [
              -92.8250023,
              46.0709618
            ],
            [
              -92.8456223,
              46.0707419
            ],
            [
              -92.8665224,
              46.0708718
            ],
            [
              -92.8873524,
              46.0709818
            ],
            [
              -92.9080923,
              46.0710418
            ],
            [
              -92.9297223,
              46.0712518
            ],
            [
              -92.92959230000001,
              46.0856818
            ],
            [
              -92.9293623,
              46.1000217
            ],
            [
              -92.9289924,
              46.1146019
            ],
            [
              -92.9285523,
              46.1290719
            ],
            [
              -92.9286423,
              46.1434118
            ],
            [
              -92.9288222,
              46.1586417
            ],
            [
              -92.9076623,
              46.1583318
            ],
            [
              -92.8866723,
              46.1582917
            ],
            [
              -92.8660223,
              46.1580919
            ],
            [
              -92.8452823,
              46.1580218
            ],
            [
              -92.82453240000001,
              46.1578919
            ],
            [
              -92.80374230000001,
              46.1577517
            ],
            [
              -92.8037922,
              46.1431017
            ],
            [
              -92.8038522,
              46.1286918
            ],
            [
              -92.8040224,
              46.1141719
            ],
            [
              -92.8041324,
              46.0996718
            ],
            [
              -92.80410230000001,
              46.0852419
            ]
          ]
        ]
      },
      "type": "Feature",
      "properties": {
        "label": "42N 20W"
      }
    }
  ]
}
