{
  "type": "FeatureCollection",
  "features": [
    {
      "geometry": {
        "type": "Polygon",
        "coordinates": [
          [
            [
              -92.68362983485976,
              47.19645557010937
            ],
            [
              -92.6841363639364,
              47.18196913735832
            ],
            [
              -92.68413798087845,
              47.18192288018926
            ],
            [
              -92.68357394047143,
              47.16752841163018
            ],
            [
              -92.68357458273549,
              47.16746109552371
            ],
            [
              -92.68371264953868,
              47.15301934726819
            ],
            [
              -92.68371319978364,
              47.15292749902799
            ],
            [
              -92.68375225699975,
              47.13850945293984
            ],
            [
              -92.68312467953018,
              47.124160219387214
            ],
            [
              -92.68312171954912,
              47.124092096501826
            ],
            [
              -92.68306011131506,
              47.10962753619211
            ],
            [
              -92.70330054833791,
              47.10951278856725
            ],
            [
              -92.70555356297719,
              47.109509625519955
            ],
            [
              -92.72478411916401,
              47.1093956579482
            ],
            [
              -92.72673563591344,
              47.1093913505553
            ],
            [
              -92.72673527744034,
              47.10946608845273
            ],
            [
              -92.74558617707065,
              47.1094093656084
            ],
            [
              -92.74566548786251,
              47.10940831205949
            ],
            [
              -92.74777246565141,
              47.10938030325696
            ],
            [
              -92.76708064129801,
              47.109183804885376
            ],
            [
              -92.76889924567094,
              47.10925048123064
            ],
            [
              -92.78776080653384,
              47.10915204312949
            ],
            [
              -92.78995621968745,
              47.109138097399615
            ],
            [
              -92.79008600575006,
              47.10913742026027
            ],
            [
              -92.80654322611798,
              47.10905036549097
            ],
            [
              -92.81126163854123,
              47.10909424054016
            ],
            [
              -92.81130726078385,
              47.1235384428393
            ],
            [
              -92.81116945084928,
              47.138139730485406
            ],
            [
              -92.81102948206707,
              47.15226114191161
            ],
            [
              -92.81102931553875,
              47.15230723807913
            ],
            [
              -92.81089209021181,
              47.166999450826744
            ],
            [
              -92.81088994598335,
              47.167113841558184
            ],
            [
              -92.81061945104277,
              47.18153531897872
            ],
            [
              -92.8104808806155,
              47.195996412323986
            ],
            [
              -92.81047913411729,
              47.196064425922536
            ],
            [
              -92.80448010915407,
              47.195986582346336
            ],
            [
              -92.80334003014391,
              47.195920471992665
            ],
            [
              -92.78907880095021,
              47.196108996852594
            ],
            [
              -92.78899268706824,
              47.19611012983011
            ],
            [
              -92.78889452114659,
              47.19611142746567
            ],
            [
              -92.76861125584556,
              47.19637774231757
            ],
            [
              -92.7684427415266,
              47.19637769001627
            ],
            [
              -92.74725663453924,
              47.19636911792482
            ],
            [
              -92.74709337852352,
              47.19636816026145
            ],
            [
              -92.7259355275397,
              47.19624207895703
            ],
            [
              -92.7258012453143,
              47.19624314120183
            ],
            [
              -92.70471580113401,
              47.196407985200906
            ],
            [
              -92.70454659246664,
              47.196408383675625
            ],
            [
              -92.68376392719249,
              47.196455425068706
            ],
            [
              -92.68362983485976,
              47.19645557010937
            ]
          ]
        ]
      },
      "type": "Feature",
      "properties": {
        "TWP_LABEL": "T54 R19W"
      }
    }
  ]
}
