{
  "type": "FeatureCollection",
  "features": [
    {
      "geometry": {
        "type": "Polygon",
        "coordinates": [
          [
            [
              -93.44878521206107,
              47.1960312264058
            ],
            [
              -93.4279801446724,
              47.196182384991495
            ],
            [
              -93.40661919626764,
              47.196188021637624
            ],
            [
              -93.4065401614513,
              47.19618803509852
            ],
            [
              -93.38513975379475,
              47.196189541016324
            ],
            [
              -93.38357680483499,
              47.19620540014132
            ],
            [
              -93.3818261586805,
              47.19625474302608
            ],
            [
              -93.36400338882935,
              47.19624916271827
            ],
            [
              -93.34277426421511,
              47.19629273380788
            ],
            [
              -93.34264225601302,
              47.19629131845821
            ],
            [
              -93.32138736888781,
              47.19618682347415
            ],
            [
              -93.32128736446538,
              47.181690780632124
            ],
            [
              -93.32128788896235,
              47.167158008880655
            ],
            [
              -93.32128807692034,
              47.167034055304576
            ],
            [
              -93.32126915894962,
              47.15267076494778
            ],
            [
              -93.32126904827408,
              47.152588141171464
            ],
            [
              -93.32128730243771,
              47.138378684296704
            ],
            [
              -93.32128803800552,
              47.13797577636232
            ],
            [
              -93.32119919728423,
              47.12365085072979
            ],
            [
              -93.32119838562636,
              47.12357022305688
            ],
            [
              -93.32105310426617,
              47.109134347634644
            ],
            [
              -93.32113227134015,
              47.10913546461984
            ],
            [
              -93.32122216172418,
              47.1091355369527
            ],
            [
              -93.34023013104846,
              47.10914880246786
            ],
            [
              -93.34268750811637,
              47.10912712132338
            ],
            [
              -93.34276880974066,
              47.109127077755865
            ],
            [
              -93.36167189117128,
              47.109115381668936
            ],
            [
              -93.36359109148174,
              47.10907571564225
            ],
            [
              -93.38274410612384,
              47.109192508827
            ],
            [
              -93.38283340374022,
              47.109193045852614
            ],
            [
              -93.38497835132597,
              47.10919518530161
            ],
            [
              -93.39008586703739,
              47.10926123842145
            ],
            [
              -93.39123789489436,
              47.10918306454536
            ],
            [
              -93.40389427517916,
              47.109177723734625
            ],
            [
              -93.40627716153011,
              47.109242104306276
            ],
            [
              -93.4063675990797,
              47.109244546758354
            ],
            [
              -93.42388503181127,
              47.10917559442755
            ],
            [
              -93.42674581291259,
              47.1091640793288
            ],
            [
              -93.44588412754344,
              47.10919967973904
            ],
            [
              -93.44880440462708,
              47.10919735257794
            ],
            [
              -93.44883887850379,
              47.12366661110008
            ],
            [
              -93.44897273593999,
              47.13809584040898
            ],
            [
              -93.44897335399209,
              47.13816243828078
            ],
            [
              -93.44897223716042,
              47.138367822390386
            ],
            [
              -93.44889544762206,
              47.15248808722903
            ],
            [
              -93.44904431888479,
              47.167109760473814
            ],
            [
              -93.44891463538634,
              47.18155251578264
            ],
            [
              -93.44878521206107,
              47.1960312264058
            ]
          ]
        ]
      },
      "type": "Feature",
      "properties": {
        "TWP_LABEL": "T54 R24W"
      }
    }
  ]
}
