{
  "type": "FeatureCollection",
  "features": [
    {
      "geometry": {
        "type": "Polygon",
        "coordinates": [
          [
            [
              -93.19271786823002,
              47.54467172992036
            ],
            [
              -93.17123105956865,
              47.54516436158808
            ],
            [
              -93.15015347435157,
              47.54482464024305
            ],
            [
              -93.12882435730462,
              47.54476925441478
            ],
            [
              -93.10722937152745,
              47.54464716216784
            ],
            [
              -93.08546170906908,
              47.54451213233713
            ],
            [
              -93.06374744782661,
              47.544489913979405
            ],
            [
              -93.06438014746094,
              47.534709814597875
            ],
            [
              -93.06411228309918,
              47.528906132539674
            ],
            [
              -93.06411217720483,
              47.52885763653889
            ],
            [
              -93.0644696203421,
              47.52352619159917
            ],
            [
              -93.0647120698536,
              47.51958935822009
            ],
            [
              -93.06496300774275,
              47.514690142791494
            ],
            [
              -93.06541881090602,
              47.50660856601022
            ],
            [
              -93.06575385354397,
              47.50026433640444
            ],
            [
              -93.06572695043768,
              47.49993313753414
            ],
            [
              -93.06560408192095,
              47.4999329412545
            ],
            [
              -93.06663358669677,
              47.4858608324334
            ],
            [
              -93.06664661046906,
              47.48568276163965
            ],
            [
              -93.06703747428625,
              47.4778574253175
            ],
            [
              -93.0673117493452,
              47.47192936082045
            ],
            [
              -93.0673220240272,
              47.47183513843273
            ],
            [
              -93.06885975569874,
              47.457729799752244
            ],
            [
              -93.08975586544283,
              47.45793159815069
            ],
            [
              -93.11130207371136,
              47.458056985660555
            ],
            [
              -93.13203575242895,
              47.456829564914614
            ],
            [
              -93.15346479418831,
              47.45785595194756
            ],
            [
              -93.17488406180799,
              47.45724482774007
            ],
            [
              -93.1750352340462,
              47.45724050029631
            ],
            [
              -93.1961033341917,
              47.45725169782907
            ],
            [
              -93.19558643549186,
              47.47186518164927
            ],
            [
              -93.1955840841746,
              47.471970047817834
            ],
            [
              -93.19525408156083,
              47.48619937949598
            ],
            [
              -93.19507797152608,
              47.49993405172242
            ],
            [
              -93.19506820961529,
              47.50069525771555
            ],
            [
              -93.19472476084954,
              47.515704303327226
            ],
            [
              -93.19407077241227,
              47.52940014306356
            ],
            [
              -93.19271786823002,
              47.54467172992036
            ]
          ]
        ]
      },
      "type": "Feature",
      "properties": {
        "TWP_LABEL": "T58 R22W"
      }
    }
  ]
}
