{
  "type": "FeatureCollection",
  "features": [
    {
      "geometry": {
        "type": "Polygon",
        "coordinates": [
          [
            [
              -92.80405492886867,
              47.717747226794245
            ],
            [
              -92.80292455659409,
              47.71773533880757
            ],
            [
              -92.79809750617196,
              47.71767285020437
            ],
            [
              -92.78170445331837,
              47.71757947217773
            ],
            [
              -92.77657674460782,
              47.71748850686326
            ],
            [
              -92.76016825637952,
              47.717329040400145
            ],
            [
              -92.75480295306525,
              47.7172548373109
            ],
            [
              -92.7352085848344,
              47.717103349806976
            ],
            [
              -92.73513132489776,
              47.71710274674252
            ],
            [
              -92.73502586775705,
              47.71709970344447
            ],
            [
              -92.73343664779732,
              47.71705382971725
            ],
            [
              -92.71690405710066,
              47.71689721093112
            ],
            [
              -92.71225312975136,
              47.71665169389019
            ],
            [
              -92.69541768112103,
              47.716734148786735
            ],
            [
              -92.69058551968561,
              47.71657724577135
            ],
            [
              -92.69038952429047,
              47.705791360696324
            ],
            [
              -92.69038650504042,
              47.70560883894703
            ],
            [
              -92.69038621931111,
              47.70550327141742
            ],
            [
              -92.69034476581105,
              47.69018709212432
            ],
            [
              -92.69033524684963,
              47.68989079910156
            ],
            [
              -92.68984998467394,
              47.67478207228492
            ],
            [
              -92.68959209276039,
              47.65989950600203
            ],
            [
              -92.6895859343598,
              47.65967114544867
            ],
            [
              -92.68918840783958,
              47.64492652860695
            ],
            [
              -92.68915558776358,
              47.63029642484579
            ],
            [
              -92.68919545378876,
              47.63003588880802
            ],
            [
              -92.71018810552074,
              47.629955726154826
            ],
            [
              -92.7314857368789,
              47.62977375041515
            ],
            [
              -92.75304775971502,
              47.629948329932084
            ],
            [
              -92.77375881828424,
              47.62997344017237
            ],
            [
              -92.7951077158318,
              47.630274888846216
            ],
            [
              -92.79927200385103,
              47.630777195240334
            ],
            [
              -92.79886121974373,
              47.64429239297306
            ],
            [
              -92.79885526462682,
              47.644488268159385
            ],
            [
              -92.79881476670108,
              47.645820281504555
            ],
            [
              -92.79872828165712,
              47.65890904645252
            ],
            [
              -92.79872463227814,
              47.659003321046505
            ],
            [
              -92.79871892825443,
              47.66032411669655
            ],
            [
              -92.79838566041985,
              47.673963701099346
            ],
            [
              -92.79835509345027,
              47.675214330051425
            ],
            [
              -92.7987654756882,
              47.68850727404297
            ],
            [
              -92.79880511879952,
              47.689791039141625
            ],
            [
              -92.79860977230379,
              47.70246130131788
            ],
            [
              -92.7985917677814,
              47.70362874184741
            ],
            [
              -92.7987888288317,
              47.70362909202355
            ],
            [
              -92.80035799117195,
              47.70790434034042
            ],
            [
              -92.80165975384276,
              47.711539242939416
            ],
            [
              -92.80405492886867,
              47.717747226794245
            ]
          ]
        ]
      },
      "type": "Feature",
      "properties": {
        "TWP_LABEL": "T60 R19W"
      }
    }
  ]
}
