{
  "type": "FeatureCollection",
  "features": [
    {
      "geometry": {
        "type": "Polygon",
        "coordinates": [
          [
            [
              -92.55852567693762,
              43.84825600574996
            ],
            [
              -92.54995860166007,
              43.84825440030931
            ],
            [
              -92.54991025594167,
              43.848254389427105
            ],
            [
              -92.5388575885879,
              43.84836244477102
            ],
            [
              -92.5387132572776,
              43.848363848738586
            ],
            [
              -92.53085890957674,
              43.848361039649824
            ],
            [
              -92.53078209118554,
              43.848361009510356
            ],
            [
              -92.51914976716887,
              43.848310837554685
            ],
            [
              -92.51893331207835,
              43.84831185714057
            ],
            [
              -92.51050321365359,
              43.84835124716606
            ],
            [
              -92.51040199439163,
              43.84835157088635
            ],
            [
              -92.49858052635388,
              43.848388771124924
            ],
            [
              -92.4985597825736,
              43.848388835433276
            ],
            [
              -92.49001108191285,
              43.848340283875345
            ],
            [
              -92.48950899867567,
              43.84833741245718
            ],
            [
              -92.47855891545,
              43.84832869804722
            ],
            [
              -92.4748286133445,
              43.84832548977052
            ],
            [
              -92.46969674473075,
              43.84829837110001
            ],
            [
              -92.46958039165229,
              43.84829846383206
            ],
            [
              -92.45832198111924,
              43.848306876364354
            ],
            [
              -92.456602575744,
              43.848308063514104
            ],
            [
              -92.44906916619095,
              43.84829056409235
            ],
            [
              -92.449303381734,
              43.834128273621
            ],
            [
              -92.44930416180547,
              43.83408123792701
            ],
            [
              -92.44918476611079,
              43.81935851803698
            ],
            [
              -92.44918400284595,
              43.81931279861941
            ],
            [
              -92.44913498825625,
              43.8050915586061
            ],
            [
              -92.44913467601243,
              43.805000972999096
            ],
            [
              -92.44913479659643,
              43.80495386088654
            ],
            [
              -92.44917214748733,
              43.790347631963975
            ],
            [
              -92.44917245206732,
              43.79023109967415
            ],
            [
              -92.44890320993723,
              43.77598968226519
            ],
            [
              -92.44890340144364,
              43.77596150333934
            ],
            [
              -92.44891587693249,
              43.775920606389576
            ],
            [
              -92.44900172144426,
              43.76144887709896
            ],
            [
              -92.46892275478385,
              43.7613900745611
            ],
            [
              -92.46914591982261,
              43.76138939615929
            ],
            [
              -92.48924031682527,
              43.76139404388258
            ],
            [
              -92.48941551728772,
              43.76139406887018
            ],
            [
              -92.50911502946677,
              43.761395220655025
            ],
            [
              -92.50933476459592,
              43.76139521509233
            ],
            [
              -92.5293980485325,
              43.76137052536653
            ],
            [
              -92.52954108287473,
              43.761370657600324
            ],
            [
              -92.54927592085666,
              43.76138718617722
            ],
            [
              -92.54946167349586,
              43.76138732556399
            ],
            [
              -92.55949350079646,
              43.76139440494438
            ],
            [
              -92.56961833731972,
              43.76137773329126
            ],
            [
              -92.56991888264221,
              43.76137655661789
            ],
            [
              -92.56978799480986,
              43.77578210148699
            ],
            [
              -92.56978698924408,
              43.775892735756436
            ],
            [
              -92.5697863725518,
              43.7759605856592
            ],
            [
              -92.56992774606405,
              43.790271952644105
            ],
            [
              -92.5699276836832,
              43.79029554689756
            ],
            [
              -92.56992725025272,
              43.790459481655176
            ],
            [
              -92.56988896168951,
              43.80493240475177
            ],
            [
              -92.56988866924281,
              43.805042881407374
            ],
            [
              -92.56988861025812,
              43.80506516374818
            ],
            [
              -92.56974394333574,
              43.819287762506434
            ],
            [
              -92.56974349340183,
              43.819355361046895
            ],
            [
              -92.57008350931957,
              43.834054380397575
            ],
            [
              -92.57008287201887,
              43.83410011370958
            ],
            [
              -92.56988557846014,
              43.84825538756085
            ],
            [
              -92.56953600642115,
              43.84825712598858
            ],
            [
              -92.55852567693762,
              43.84825600574996
            ]
          ]
        ]
      },
      "type": "Feature",
      "properties": {
        "TWP_LABEL": "T104 R14W"
      }
    }
  ]
}
