{
  "type": "FeatureCollection",
  "features": [
    {
      "geometry": {
        "type": "Polygon",
        "coordinates": [
          [
            [
              -94.01227429791508,
              44.89179750753722
            ],
            [
              -94.01012287787445,
              44.89175128887354
            ],
            [
              -94.01004470591366,
              44.891749580555995
            ],
            [
              -94.01005453039782,
              44.88403461679183
            ],
            [
              -94.00997149358624,
              44.87699039669365
            ],
            [
              -94.00997133300994,
              44.8769675501476
            ],
            [
              -94.00986636515823,
              44.862024115981356
            ],
            [
              -94.00992118977372,
              44.84775409771939
            ],
            [
              -94.00992135827896,
              44.84771025245663
            ],
            [
              -94.00996581278787,
              44.840958392625026
            ],
            [
              -94.00999305622993,
              44.83938293468909
            ],
            [
              -94.01010306440777,
              44.83310338780467
            ],
            [
              -94.01010189736768,
              44.83303608676585
            ],
            [
              -94.01003176522939,
              44.81860937630637
            ],
            [
              -94.01002982491184,
              44.818497262149364
            ],
            [
              -94.00998965317378,
              44.80402594739048
            ],
            [
              -94.01002126526501,
              44.80402583307627
            ],
            [
              -94.02032686095909,
              44.80401146637455
            ],
            [
              -94.03056921037799,
              44.803996266341805
            ],
            [
              -94.04049563959455,
              44.8040481767158
            ],
            [
              -94.04185488597233,
              44.8040234662765
            ],
            [
              -94.0447315865216,
              44.80401874757861
            ],
            [
              -94.05067481095739,
              44.80405378133946
            ],
            [
              -94.05073868200019,
              44.80405381277032
            ],
            [
              -94.0711595561672,
              44.80406203015117
            ],
            [
              -94.07125400369586,
              44.804062379925504
            ],
            [
              -94.09129678891692,
              44.804134838293905
            ],
            [
              -94.09142397558155,
              44.80413581460031
            ],
            [
              -94.11206475204798,
              44.80429237893082
            ],
            [
              -94.11209825870634,
              44.804292630050924
            ],
            [
              -94.13157257740863,
              44.804651727307736
            ],
            [
              -94.13148602321724,
              44.819213806075716
            ],
            [
              -94.13148609816217,
              44.81934647559954
            ],
            [
              -94.13149433826209,
              44.833864975100404
            ],
            [
              -94.13149558917532,
              44.83393193040577
            ],
            [
              -94.13137767186133,
              44.84858392588387
            ],
            [
              -94.13137695835114,
              44.8486739499331
            ],
            [
              -94.13135254167166,
              44.863077562715965
            ],
            [
              -94.13135246171197,
              44.863098857726094
            ],
            [
              -94.13129763569086,
              44.877706268115986
            ],
            [
              -94.13129729747558,
              44.87774751395046
            ],
            [
              -94.13117961548988,
              44.892099721814475
            ],
            [
              -94.11459998250285,
              44.89199131746309
            ],
            [
              -94.11426117209406,
              44.89198879129217
            ],
            [
              -94.11230823378538,
              44.89197421057602
            ],
            [
              -94.094067277328,
              44.891836409281254
            ],
            [
              -94.09382622040188,
              44.891834568700716
            ],
            [
              -94.09201322722957,
              44.8918227974538
            ],
            [
              -94.07320465245705,
              44.89169897986853
            ],
            [
              -94.07165886161238,
              44.891688666052595
            ],
            [
              -94.07149703708004,
              44.89168968397759
            ],
            [
              -94.05326767863295,
              44.891802884104195
            ],
            [
              -94.05101356922822,
              44.891823646798166
            ],
            [
              -94.05094519154282,
              44.89181709721138
            ],
            [
              -94.03254819184346,
              44.89183223054563
            ],
            [
              -94.03092938014652,
              44.8918334203025
            ],
            [
              -94.03071659466521,
              44.89183321179317
            ],
            [
              -94.01306747311934,
              44.89181453696204
            ],
            [
              -94.01227429791508,
              44.89179750753722
            ]
          ]
        ]
      },
      "type": "Feature",
      "properties": {
        "TWP_LABEL": "T116 R27W"
      }
    }
  ]
}
