{
  "type": "FeatureCollection",
  "features": [
    {
      "geometry": {
        "type": "Polygon",
        "coordinates": [
          [
            [
              -96.49340578118874,
              45.585507628606955
            ],
            [
              -96.49051425108709,
              45.58558336196227
            ],
            [
              -96.49041839924777,
              45.58558587120352
            ],
            [
              -96.47358688504089,
              45.58548816053952
            ],
            [
              -96.47353816390354,
              45.58548787409464
            ],
            [
              -96.46909498758447,
              45.585473501814064
            ],
            [
              -96.46905374801965,
              45.585473367606
            ],
            [
              -96.45310266230231,
              45.58533038940485
            ],
            [
              -96.45295543013076,
              45.585333288976145
            ],
            [
              -96.44825019102437,
              45.585425853197336
            ],
            [
              -96.44823296632951,
              45.58542619169486
            ],
            [
              -96.43221553858677,
              45.585549220078164
            ],
            [
              -96.43216960303546,
              45.58554956967038
            ],
            [
              -96.42793633086207,
              45.585517924880705
            ],
            [
              -96.42641790587538,
              45.58550653594804
            ],
            [
              -96.41160350230527,
              45.585318188904054
            ],
            [
              -96.41145995237038,
              45.58531635441422
            ],
            [
              -96.40635122759551,
              45.585521106040474
            ],
            [
              -96.4063328705086,
              45.58552184135631
            ],
            [
              -96.39078488330374,
              45.585394247681165
            ],
            [
              -96.39076561833147,
              45.5853940882684
            ],
            [
              -96.38562790405902,
              45.58546276888635
            ],
            [
              -96.38557552795953,
              45.58546346785487
            ],
            [
              -96.37018909595218,
              45.58528926208342
            ],
            [
              -96.3701552783253,
              45.57096057521134
            ],
            [
              -96.37015586492066,
              45.57087376547512
            ],
            [
              -96.37025349835262,
              45.5564371841203
            ],
            [
              -96.37025370691269,
              45.556406371064796
            ],
            [
              -96.37019005365983,
              45.54196307227559
            ],
            [
              -96.37019050299287,
              45.54194058012884
            ],
            [
              -96.37012484792291,
              45.52760971053717
            ],
            [
              -96.3701261966464,
              45.527542233962215
            ],
            [
              -96.36990956780748,
              45.513262364965115
            ],
            [
              -96.36990570742536,
              45.51300770329249
            ],
            [
              -96.36990536519774,
              45.512984882292756
            ],
            [
              -96.36991136898565,
              45.512782776373484
            ],
            [
              -96.36993266643483,
              45.50522383300345
            ],
            [
              -96.36983895259345,
              45.5035131975341
            ],
            [
              -96.369909975661,
              45.49996375448554
            ],
            [
              -96.36978700055565,
              45.49996375443943
            ],
            [
              -96.3697582737977,
              45.498602403898495
            ],
            [
              -96.36980560253488,
              45.49860255514762
            ],
            [
              -96.39054689493118,
              45.49876248476307
            ],
            [
              -96.39061080230763,
              45.498762971698966
            ],
            [
              -96.41110112017861,
              45.499055410682246
            ],
            [
              -96.41115534482074,
              45.49905617968662
            ],
            [
              -96.43163297147326,
              45.4992070200863
            ],
            [
              -96.43189536969932,
              45.49920892906121
            ],
            [
              -96.44863638730321,
              45.49948859572579
            ],
            [
              -96.45133418275094,
              45.49963002484597
            ],
            [
              -96.4520102848552,
              45.499631960366244
            ],
            [
              -96.4693111371655,
              45.49968012452187
            ],
            [
              -96.47279396509347,
              45.499663413095284
            ],
            [
              -96.47298459791645,
              45.499662495324
            ],
            [
              -96.47798823511413,
              45.49996382196017
            ],
            [
              -96.47933847219075,
              45.499963819026505
            ],
            [
              -96.48133849934966,
              45.49996382038037
            ],
            [
              -96.48333853853465,
              45.49996382133003
            ],
            [
              -96.48420571505592,
              45.4999638263995
            ],
            [
              -96.4929686578587,
              45.50012507306454
            ],
            [
              -96.49296990999511,
              45.500147910483726
            ],
            [
              -96.49303087939974,
              45.514236216537405
            ],
            [
              -96.49303212519749,
              45.514523506136676
            ],
            [
              -96.4930344858403,
              45.51456708333898
            ],
            [
              -96.49303241364068,
              45.51459001984
            ],
            [
              -96.49303949839293,
              45.514863215714286
            ],
            [
              -96.49322209525812,
              45.52190238245354
            ],
            [
              -96.49331454304127,
              45.52921426839218
            ],
            [
              -96.49331510766004,
              45.5292589056404
            ],
            [
              -96.49312458008315,
              45.54356383883431
            ],
            [
              -96.4932190443788,
              45.55805110703952
            ],
            [
              -96.49321975828653,
              45.55816043549391
            ],
            [
              -96.49331377972827,
              45.57253834326129
            ],
            [
              -96.49331388678972,
              45.5725534714332
            ],
            [
              -96.49340578118874,
              45.585507628606955
            ]
          ]
        ]
      },
      "type": "Feature",
      "properties": {
        "TWP_LABEL": "T124 R46W"
      }
    }
  ]
}
