{
  "type": "FeatureCollection",
  "features": [
    {
      "geometry": {
        "type": "Polygon",
        "coordinates": [
          [
            [
              -94.5438076,
              47.3311585
            ],
            [
              -94.54374150000001,
              47.3323065
            ],
            [
              -94.5436143,
              47.3344224
            ],
            [
              -94.5435934,
              47.3348164
            ],
            [
              -94.5433753,
              47.3384605
            ],
            [
              -94.5433711,
              47.3421494
            ],
            [
              -94.5433669,
              47.3458384
            ],
            [
              -94.5433659,
              47.3469793
            ],
            [
              -94.5433758,
              47.3480733
            ],
            [
              -94.54338770000001,
              47.3495533
            ],
            [
              -94.5434195,
              47.3532413
            ],
            [
              -94.5434544,
              47.3569042
            ],
            [
              -94.5434882,
              47.3605662
            ],
            [
              -94.5435231,
              47.3642281
            ],
            [
              -94.543558,
              47.3678912
            ],
            [
              -94.5435898,
              47.371285
            ],
            [
              -94.5435957,
              47.371976
            ],
            [
              -94.5435877,
              47.3747461
            ],
            [
              -94.5453926,
              47.377461
            ],
            [
              -94.5454196,
              47.377985
            ],
            [
              -94.5454645,
              47.381527
            ],
            [
              -94.5456769,
              47.3954539
            ],
            [
              -94.5459161,
              47.4108607
            ],
            [
              -94.5328783,
              47.4111628
            ],
            [
              -94.5275527,
              47.4112846
            ],
            [
              -94.5222284,
              47.4114077
            ],
            [
              -94.5189361,
              47.4114907
            ],
            [
              -94.51701,
              47.4115396
            ],
            [
              -94.5115896,
              47.4116848
            ],
            [
              -94.5062652,
              47.4118268
            ],
            [
              -94.5009377,
              47.4119218
            ],
            [
              -94.4957033,
              47.4119017
            ],
            [
              -94.490469,
              47.4118747
            ],
            [
              -94.4902541,
              47.4118737
            ],
            [
              -94.49024510000001,
              47.4118737
            ],
            [
              -94.489972,
              47.4118699
            ],
            [
              -94.4852347,
              47.4118467
            ],
            [
              -94.4800004,
              47.4118207
            ],
            [
              -94.4747459,
              47.4117968
            ],
            [
              -94.4694916,
              47.4117728
            ],
            [
              -94.46409220000001,
              47.4117448
            ],
            [
              -94.4586919,
              47.4117158
            ],
            [
              -94.4533494,
              47.4117128
            ],
            [
              -94.4480071,
              47.4117098
            ],
            [
              -94.4426638,
              47.4117069
            ],
            [
              -94.4373214,
              47.4117029
            ],
            [
              -94.43203410000001,
              47.4117269
            ],
            [
              -94.4267466,
              47.4117508
            ],
            [
              -94.4214593,
              47.411775
            ],
            [
              -94.4160709,
              47.4118098
            ],
            [
              -94.4160801,
              47.4079349
            ],
            [
              -94.4160894,
              47.4043189
            ],
            [
              -94.4160835,
              47.400702
            ],
            [
              -94.4160776,
              47.3977301
            ],
            [
              -94.41607660000001,
              47.3974141
            ],
            [
              -94.41607660000001,
              47.3971579
            ],
            [
              -94.41604980000001,
              47.393463
            ],
            [
              -94.4160417,
              47.3926331
            ],
            [
              -94.4160409,
              47.3924641
            ],
            [
              -94.4160159,
              47.389781
            ],
            [
              -94.4159291,
              47.3862831
            ],
            [
              -94.4158733,
              47.3826031
            ],
            [
              -94.4159764,
              47.3787172
            ],
            [
              -94.4160746,
              47.3749962
            ],
            [
              -94.4161759,
              47.3711522
            ],
            [
              -94.4162099,
              47.3698762
            ],
            [
              -94.416229,
              47.3691753
            ],
            [
              -94.4162759,
              47.3673883
            ],
            [
              -94.416325,
              47.3659193
            ],
            [
              -94.4163961,
              47.3637582
            ],
            [
              -94.4163983,
              47.3637153
            ],
            [
              -94.4164152,
              47.3631774
            ],
            [
              -94.4165284,
              47.3616254
            ],
            [
              -94.4165193,
              47.3600424
            ],
            [
              -94.41653860000001,
              47.3564574
            ],
            [
              -94.4165577,
              47.3528713
            ],
            [
              -94.4164779,
              47.3493184
            ],
            [
              -94.41651,
              47.3477314
            ],
            [
              -94.416513,
              47.3475704
            ],
            [
              -94.416551,
              47.3456835
            ],
            [
              -94.4165941,
              47.3436345
            ],
            [
              -94.4166011,
              47.3432764
            ],
            [
              -94.4166263,
              47.3420474
            ],
            [
              -94.4166424,
              47.3384965
            ],
            [
              -94.41664440000001,
              47.3364435
            ],
            [
              -94.41664440000001,
              47.3364414
            ],
            [
              -94.4166395,
              47.3349195
            ],
            [
              -94.4166367,
              47.3313436
            ],
            [
              -94.4166348,
              47.3277675
            ],
            [
              -94.4166489,
              47.3265956
            ],
            [
              -94.416655,
              47.3260336
            ],
            [
              -94.416632,
              47.3241906
            ],
            [
              -94.4198993,
              47.3241846
            ],
            [
              -94.42195430000001,
              47.3241806
            ],
            [
              -94.4220744,
              47.3241796
            ],
            [
              -94.4243506,
              47.3241516
            ],
            [
              -94.4244776,
              47.3241496
            ],
            [
              -94.4287398,
              47.3240976
            ],
            [
              -94.4337391,
              47.3240567
            ],
            [
              -94.4372374,
              47.3240337
            ],
            [
              -94.4387575,
              47.3240166
            ],
            [
              -94.4403627,
              47.3240035
            ],
            [
              -94.44072460000001,
              47.3239995
            ],
            [
              -94.4437248,
              47.3239836
            ],
            [
              -94.4480561,
              47.3239657
            ],
            [
              -94.4487322,
              47.3239566
            ],
            [
              -94.4539435,
              47.3239387
            ],
            [
              -94.4588748,
              47.3239157
            ],
            [
              -94.4593938,
              47.3239177
            ],
            [
              -94.4646932,
              47.3239016
            ],
            [
              -94.4699565,
              47.3238926
            ],
            [
              -94.4752589,
              47.3238706
            ],
            [
              -94.48052220000001,
              47.3238607
            ],
            [
              -94.4858647,
              47.3237886
            ],
            [
              -94.4911679,
              47.3237886
            ],
            [
              -94.4965023,
              47.3236986
            ],
            [
              -94.5017016,
              47.3236456
            ],
            [
              -94.5071721,
              47.3235856
            ],
            [
              -94.5125076,
              47.3235276
            ],
            [
              -94.517961,
              47.3235006
            ],
            [
              -94.5230733,
              47.3234756
            ],
            [
              -94.5285648,
              47.3234406
            ],
            [
              -94.5338841,
              47.3234066
            ],
            [
              -94.5357953,
              47.3233947
            ],
            [
              -94.53904270000001,
              47.3233736
            ],
            [
              -94.54108570000001,
              47.3233606
            ],
            [
              -94.5443199,
              47.3233397
            ],
            [
              -94.5440637,
              47.3272485
            ],
            [
              -94.5438376,
              47.3307106
            ],
            [
              -94.5438235,
              47.3309235
            ],
            [
              -94.5438076,
              47.3311585
            ]
          ]
        ]
      },
      "type": "Feature",
      "properties": {
        "label": "145N 30W"
      }
    }
  ]
}
