{
  "type": "FeatureCollection",
  "features": [
    {
      "geometry": {
        "type": "Polygon",
        "coordinates": [
          [
            [
              -95.32111911199159,
              47.84782867985196
            ],
            [
              -95.30117845201976,
              47.84790628510704
            ],
            [
              -95.27953945967133,
              47.847969174054285
            ],
            [
              -95.2580601510984,
              47.84801583900313
            ],
            [
              -95.236696945369,
              47.848034471344846
            ],
            [
              -95.23641904258062,
              47.84803468790462
            ],
            [
              -95.21501464279737,
              47.84796392782923
            ],
            [
              -95.19355294465585,
              47.847800285878066
            ],
            [
              -95.19367707602224,
              47.83331085610003
            ],
            [
              -95.19373301652824,
              47.81878670505708
            ],
            [
              -95.19386853029565,
              47.804305991613106
            ],
            [
              -95.19387035751878,
              47.804108271748554
            ],
            [
              -95.19387859420226,
              47.80321701429059
            ],
            [
              -95.19398592844314,
              47.78959163813706
            ],
            [
              -95.19398585126422,
              47.789443014380716
            ],
            [
              -95.19397849504563,
              47.7751405883456
            ],
            [
              -95.19398014757857,
              47.7750274979866
            ],
            [
              -95.19419183786046,
              47.760541312119614
            ],
            [
              -95.19419148888046,
              47.7604464269659
            ],
            [
              -95.20380828241241,
              47.7605479025223
            ],
            [
              -95.21586929256064,
              47.76058289823399
            ],
            [
              -95.22676296140659,
              47.76060741898158
            ],
            [
              -95.23714110289949,
              47.76065664541201
            ],
            [
              -95.23743106344426,
              47.76065565212668
            ],
            [
              -95.25897029693436,
              47.76057985914847
            ],
            [
              -95.2731059287811,
              47.76069374284568
            ],
            [
              -95.27480730515622,
              47.76070729499012
            ],
            [
              -95.28050841109332,
              47.76070852788936
            ],
            [
              -95.29185787702464,
              47.76063927970916
            ],
            [
              -95.30198348729668,
              47.760607456632485
            ],
            [
              -95.30216806718148,
              47.760606868233715
            ],
            [
              -95.3230775313269,
              47.76065519851751
            ],
            [
              -95.3228644083132,
              47.77522225773122
            ],
            [
              -95.32258351467634,
              47.7896429175798
            ],
            [
              -95.32202270918337,
              47.80427682888668
            ],
            [
              -95.32193242224959,
              47.818729889531376
            ],
            [
              -95.32146105312432,
              47.833325601709724
            ],
            [
              -95.32111911199159,
              47.84782867985196
            ]
          ]
        ]
      },
      "type": "Feature",
      "properties": {
        "TWP_LABEL": "T150 R36W"
      }
    }
  ]
}
