{
  "type": "FeatureCollection",
  "features": [
    {
      "geometry": {
        "type": "Polygon",
        "coordinates": [
          [
            [
              -95.21124782441231,
              48.45287913469894
            ],
            [
              -95.19031787939764,
              48.45286130580674
            ],
            [
              -95.18991552115008,
              48.45286079022442
            ],
            [
              -95.18921125638853,
              48.452859884390364
            ],
            [
              -95.16855896046904,
              48.452909287034075
            ],
            [
              -95.16707203666041,
              48.452910324655996
            ],
            [
              -95.16666571806638,
              48.45291221723289
            ],
            [
              -95.14677449397264,
              48.45300311272816
            ],
            [
              -95.14548939340854,
              48.45300910088017
            ],
            [
              -95.12474297738568,
              48.4530523863425
            ],
            [
              -95.12360545687564,
              48.45301941261686
            ],
            [
              -95.12349348546508,
              48.453020154196665
            ],
            [
              -95.10309272961558,
              48.453153447940984
            ],
            [
              -95.10196984089902,
              48.45314698527483
            ],
            [
              -95.08162426564665,
              48.45328762998996
            ],
            [
              -95.0803080555394,
              48.45329795124874
            ],
            [
              -95.0797563831246,
              48.45329859045024
            ],
            [
              -95.0797420167197,
              48.43869220577499
            ],
            [
              -95.07983377900463,
              48.42421033224386
            ],
            [
              -95.07982973574957,
              48.42411005379506
            ],
            [
              -95.0792372335003,
              48.4095484008917
            ],
            [
              -95.07923589600682,
              48.40948039312695
            ],
            [
              -95.07974416820835,
              48.395384810474994
            ],
            [
              -95.079745931995,
              48.39517054582418
            ],
            [
              -95.07986453124775,
              48.380767090778896
            ],
            [
              -95.0798666126182,
              48.38051438563371
            ],
            [
              -95.0799636058564,
              48.36669022241897
            ],
            [
              -95.09908383920637,
              48.366530986915144
            ],
            [
              -95.09935177398259,
              48.36652873293102
            ],
            [
              -95.10185846050481,
              48.36651645734085
            ],
            [
              -95.10196062746653,
              48.36651595585608
            ],
            [
              -95.12015436543724,
              48.366470891786854
            ],
            [
              -95.12071351639766,
              48.36647670912783
            ],
            [
              -95.12310697260153,
              48.366501579608006
            ],
            [
              -95.12321299180927,
              48.36649711838279
            ],
            [
              -95.12372459779918,
              48.36647558892364
            ],
            [
              -95.14241420297104,
              48.36635632492638
            ],
            [
              -95.1454213242534,
              48.36636306262447
            ],
            [
              -95.16392157091825,
              48.366332159143504
            ],
            [
              -95.16402849712775,
              48.366332512760984
            ],
            [
              -95.16653062365377,
              48.366340759190884
            ],
            [
              -95.16695797237436,
              48.36634016522358
            ],
            [
              -95.18614902546861,
              48.366311854469245
            ],
            [
              -95.18872718792993,
              48.36630780707297
            ],
            [
              -95.18891220008399,
              48.366307514403495
            ],
            [
              -95.20660963076385,
              48.366205892286274
            ],
            [
              -95.20672715071386,
              48.36620520835877
            ],
            [
              -95.21057276571622,
              48.36627413471914
            ],
            [
              -95.21065497835609,
              48.36627399897521
            ],
            [
              -95.21103630396706,
              48.379632853310646
            ],
            [
              -95.21106692965556,
              48.38071199518006
            ],
            [
              -95.21113066592795,
              48.3940724252487
            ],
            [
              -95.21114099843247,
              48.39516995059444
            ],
            [
              -95.2112478067789,
              48.40868248449569
            ],
            [
              -95.2112557628547,
              48.4095101216052
            ],
            [
              -95.21133581201472,
              48.42312211585608
            ],
            [
              -95.211345008077,
              48.424192665190745
            ],
            [
              -95.21129631043542,
              48.43750118439586
            ],
            [
              -95.21129200644782,
              48.43868896086919
            ],
            [
              -95.21129172342148,
              48.43878438651845
            ],
            [
              -95.21125205145651,
              48.45217723593895
            ],
            [
              -95.21124782441231,
              48.45287913469894
            ]
          ]
        ]
      },
      "type": "Feature",
      "properties": {
        "TWP_LABEL": "T157 R35W"
      }
    }
  ]
}
